compactor/__init__.py
compactor/context.py
compactor/httpd.py
compactor/pid.py
compactor/process.py
compactor/request.py
compactor/testing.py
compactor-0.3.0.dist-info/DESCRIPTION.rst
compactor-0.3.0.dist-info/METADATA
compactor-0.3.0.dist-info/metadata.json
compactor-0.3.0.dist-info/RECORD
compactor-0.3.0.dist-info/top_level.txt
compactor-0.3.0.dist-info/WHEEL
compactor-0.3.0.dist-info/zip-safe
