Metadata-Version: 2.0
Name: compactor
Version: 0.3.0
Summary: Pure python implementation of libprocess actors
Home-page: http://github.com/wickman/compactor
Author: Brian Wickman
Author-email: wickman@gmail.com
License: Apache License 2.0
Platform: UNKNOWN
Requires-Dist: trollius
Requires-Dist: tornado (==4.1)
Requires-Dist: twitter.common.lang
Provides-Extra: pb
Requires-Dist: protobuf (>=2.6.1,<2.7); extra == 'pb'
